usermanagement/__init__.py
usermanagement/asgi.py
usermanagement/settings.py
usermanagement/urls.py
usermanagement/views.py
usermanagement/wsgi.py
usermanagement/core/__init__.py
usermanagement/core/admin.py
usermanagement/core/apps.py
usermanagement/core/forms.py
usermanagement/core/models.py
usermanagement/core/signals.py
usermanagement/core/tests.py
usermanagement/core/urls.py
usermanagement/core/views.py
usermanagement/core/migrations/0001_initial.py
usermanagement/core/migrations/__init__.py
usermanagement/core/templates/__init__.py
usermanagement/core/templates/profile.html
usermanagement/core/templates/profile_edit.html
usermanagement/core/templates/profile_settings.html
usermanagement/static/favicon.ico
usermanagement/static/assets/css/style.css
usermanagement/static/assets/js/main.js
usermanagement/static/assets/scss/Readme.txt
usermanagement/static/css/style.css
usermanagement/static/images/ape1.jpg
usermanagement/static/images/ape2.jpg
usermanagement/static/images/avatar.svg
usermanagement/static/images/logo.svg
usermanagement/templates/404.html
usermanagement/templates/base.html
usermanagement/templates/home.html
usermanagement/templates/sidebar.html
usermanagement/templates/allauth/layouts/base.html
usermanagement/templates/includes/footer.html
usermanagement/templates/includes/header.html
usermanagement/templates/includes/messages.html
usermanagement/templates/layouts/blank.html
usermanagement/templates/layouts/box.html
django_usermanagement_interface-1.4.3.dist-info/LICENSE
django_usermanagement_interface-1.4.3.dist-info/METADATA
django_usermanagement_interface-1.4.3.dist-info/WHEEL
django_usermanagement_interface-1.4.3.dist-info/top_level.txt
django_usermanagement_interface-1.4.3.dist-info/RECORD
