Metadata-Version: 2.1
Name: django_usermanagement_interface
Version: 1.4.3
Summary: A Django app to manage users
Home-page: 
Author: Hamed Jamali
Author-email: hamed.jamali.software@gmail.com
License: MIT
Keywords: django,user,management
Classifier: Environment :: Web Environment
Classifier: Framework :: Django
Classifier: Framework :: Django :: 5.0
Classifier: Intended Audience :: Developers
Classifier: License :: OSI Approved :: MIT License
Classifier: Operating System :: OS Independent
Classifier: Programming Language :: Python
Classifier: Programming Language :: Python :: 3
Classifier: Programming Language :: Python :: 3.8
Classifier: Programming Language :: Python :: 3.9
Classifier: Topic :: Internet :: WWW/HTTP
Classifier: Topic :: Internet :: WWW/HTTP :: Dynamic Content
Classifier: Topic :: Software Development :: Libraries :: Application Frameworks
License-File: LICENSE
Requires-Dist: Django >=5.0
Requires-Dist: django-bootstrap5
Requires-Dist: pillow
Requires-Dist: django-cleanup
Requires-Dist: django-allauth
Requires-Dist: django-htmx
Requires-Dist: pyjwt
Requires-Dist: cryptography
